odoo8_addon_web_widget_radio_tree-8.0.1.0.0.99.dev8-py2.7-nspkg.pth
odoo8_addon_web_widget_radio_tree-8.0.1.0.0.99.dev8.dist-info/METADATA
odoo8_addon_web_widget_radio_tree-8.0.1.0.0.99.dev8.dist-info/RECORD
odoo8_addon_web_widget_radio_tree-8.0.1.0.0.99.dev8.dist-info/WHEEL
odoo8_addon_web_widget_radio_tree-8.0.1.0.0.99.dev8.dist-info/namespace_packages.txt
odoo8_addon_web_widget_radio_tree-8.0.1.0.0.99.dev8.dist-info/top_level.txt
odoo_addons/web_widget_radio_tree/README.rst
odoo_addons/web_widget_radio_tree/__init__.py
odoo_addons/web_widget_radio_tree/__openerp__.py
odoo_addons/web_widget_radio_tree/i18n/web_widget_radio_tree.pot
odoo_addons/web_widget_radio_tree/static/description/icon.png
odoo_addons/web_widget_radio_tree/static/src/js/widget.js
odoo_addons/web_widget_radio_tree/static/src/xml/widget.xml
odoo_addons/web_widget_radio_tree/views/assets.xml
