Metadata-Version: 2.1
Name: odoo8-addon-web-widget-radio-tree
Version: 8.0.1.0.0.99.dev8
Summary: Add radio buttons for records in tree.
Home-page: http://www.bloopark.de
Author: bloopark systems GmbH & Co. KG, Odoo Community Association (OCA)
Author-email: support@odoo-community.org
License: AGPL-3
Platform: UNKNOWN
Classifier: Programming Language :: Python
Classifier: Framework :: Odoo
Classifier: License :: OSI Approved :: GNU Affero General Public License v3
Requires-Python: ~=2.7
Requires-Dist: odoo (<9.0a,>=8.0a)
